Volavola/__init__.py
Volavola/main.py
Volavola-1.6.dist-info/LICENSE
Volavola-1.6.dist-info/METADATA
Volavola-1.6.dist-info/WHEEL
Volavola-1.6.dist-info/top_level.txt
Volavola-1.6.dist-info/RECORD
